CHANGES.rst
CONTRIBUTORS.rst
DEVELOP.rst
LICENSE.rst
MANIFEST.in
README.rst
setup.cfg
setup.py
docs/index.rst
src/operun/__init__.py
src/operun.contactform.egg-info/PKG-INFO
src/operun.contactform.egg-info/SOURCES.txt
src/operun.contactform.egg-info/dependency_links.txt
src/operun.contactform.egg-info/entry_points.txt
src/operun.contactform.egg-info/namespace_packages.txt
src/operun.contactform.egg-info/not-zip-safe
src/operun.contactform.egg-info/requires.txt
src/operun.contactform.egg-info/top_level.txt
src/operun/contactform/__init__.py
src/operun/contactform/configure.zcml
src/operun/contactform/interfaces.py
src/operun/contactform/setuphandlers.py
src/operun/contactform/testing.py
src/operun/contactform/browser/__init__.py
src/operun/contactform/browser/configure.zcml
src/operun/contactform/browser/contactform.py
src/operun/contactform/browser/mail.py
src/operun/contactform/browser/mail_templates/mailto_admin.pt
src/operun/contactform/browser/mail_templates/mailto_user.pt
src/operun/contactform/browser/overrides/.gitkeep
src/operun/contactform/browser/static/.gitkeep
src/operun/contactform/browser/static/contact_map.png
src/operun/contactform/browser/static/contactform-compiled.css
src/operun/contactform/browser/static/contactform-compiled.js
src/operun/contactform/browser/static/contactform.js
src/operun/contactform/browser/static/contactform.less
src/operun/contactform/browser/templates/contactform.pt
src/operun/contactform/browser/templates/contactform_success.pt
src/operun/contactform/locales/operun.contactform.pot
src/operun/contactform/locales/update.sh
src/operun/contactform/locales/de/LC_MESSAGES/operun.contactform.po
src/operun/contactform/profiles/default/browserlayer.xml
src/operun/contactform/profiles/default/metadata.xml
src/operun/contactform/profiles/default/registry.xml
src/operun/contactform/profiles/testing/metadata.xml
src/operun/contactform/profiles/uninstall/browserlayer.xml
src/operun/contactform/tests/__init__.py
src/operun/contactform/tests/test_contactform.py
src/operun/contactform/tests/test_robot.py
src/operun/contactform/tests/test_setup.py
src/operun/contactform/tests/robot/keywords.robot
src/operun/contactform/tests/robot/test_contactform.robot
src/operun/contactform/tests/robot/test_example.robot
src/operun/contactform/tests/robot/variables.py