Metadata-Version: 1.1
Name: operun.contactform
Version: 1.0.0a2
Summary: A Plone Contact-Form Add-On.
Home-page: https://pypi.python.org/pypi/operun.contactform
Author: Jesse Stippel
Author-email: jesse.stippel@operun.de
License: GPL version 2
Keywords: Python Plone
Platform: UNKNOWN
Classifier: Environment :: Web Environment
Classifier: Framework :: Plone
Classifier: Framework :: Plone :: 5.0
Classifier: Framework :: Plone :: 5.1
Classifier: Programming Language :: Python
Classifier: Programming Language :: Python :: 2.7
Classifier: Operating System :: OS Independent
Classifier: License :: OSI Approved :: GNU General Public License v2 (GPLv2)
